pytokenx/__init__.py
pytokenx/base.py
pytokenx/file_storage.py
pytokenx/sqlalchemy_storage.py
pytokenx-1.6.1.dist-info/METADATA
pytokenx-1.6.1.dist-info/WHEEL
pytokenx-1.6.1.dist-info/top_level.txt
pytokenx-1.6.1.dist-info/RECORD
