Metadata-Version: 2.1
Name: pytokenx
Version: 1.6.1
Summary: A token manager for Python
Author-email: timway <tianmh2013@163.com>
Project-URL: Homepage, https://github.com/tian-minghui/pytokenx
Classifier: Programming Language :: Python :: 3
Classifier: License :: OSI Approved :: MIT License
Classifier: Operating System :: OS Independent
Requires-Python: >=3.8
